person/__init__.py
person/descriptor.py
person/main.py
person_descriptor-0.1.0.dist-info/METADATA
person_descriptor-0.1.0.dist-info/WHEEL
person_descriptor-0.1.0.dist-info/entry_points.txt
person_descriptor-0.1.0.dist-info/top_level.txt
person_descriptor-0.1.0.dist-info/RECORD
